src/__init__.py
src/cli.py
mindedge_model_tool-0.1.0.dist-info/METADATA
mindedge_model_tool-0.1.0.dist-info/WHEEL
mindedge_model_tool-0.1.0.dist-info/entry_points.txt
mindedge_model_tool-0.1.0.dist-info/RECORD
