Metadata-Version: 2.4
Name: mindedge-model-tool
Version: 0.1.0
Summary: A command line tool for downloading files from MinIO
Author: luxu1220
Author-email: luxu1220@gmail.com
Requires-Python: >=3.10
Classifier: Programming Language :: Python :: 3
Classifier: Programming Language :: Python :: 3.10
Classifier: Programming Language :: Python :: 3.11
Classifier: Programming Language :: Python :: 3.12
Classifier: Programming Language :: Python :: 3.13
Classifier: Programming Language :: Python :: 3.14
Requires-Dist: minio (>=7.0.0)
